{
  "url": "https://lite.cnn.com/2026/03/09/politics/kevin-kiley-independent-republican",
  "title": "California congressman is leaving the Republican Party to become an independent amid tough reelection race | CNN Politics",
  "date": "2026-03-10T07:12:00.396076+00:00",
  "authors": [
    "Aileen Graef",
    "Alison Main"
  ],
  "text": "Source: CNN\n\nRep. Kevin Kiley has announced he is leaving the Republican Party effective immediately, making him the only independent member of the US House of Representatives.\n\nThe move comes as the California lawmaker is facing a tough bid for reelection in the wake of redistricting in the state led by Democratic Gov. Gavin Newsom. The decision by the congressman will officially shrink Speaker Mike Johnson’salready razor-thin GOP majority. Kiley, however, will still caucus with Republicans in the chamber, meaning the switch in his party affiliation may not have a significant impact on vote math in the House.\n\nPressed on if he’ll continue to be a reliable vote for Johnson, who is operating with the narrowest House margin in decades, Kiley noted that he has already crossed party lines, including on votes to rein in the president’s tariff authorities.\n\n“I approach, you know, every vote with, you know, a mind towards how it’s going to impact the folks that I represent,” he told reporters on Monday.\n\nKiley said that he has already changed his registration in California to “no party preference” and has asked the House clerk to change how he is identified in the official roster.\n\nThe House has been operating with 218 Republicans, including Kiley, and 214 Democrats, which means Johnson has been able to affordonly afford a single defectionon party-line votes.\n\nThe California lawmaker, who has broken with his party on several key issues in his two terms in Congress, said he’ll continue to caucus with House Republicans for the remainder of this term, given that committee assignments are linked to party affiliation.\n\n“I will remain caucusing with the Republicans … for those administrative purposes, but in terms of the way that I approach my role here. I am an independent, and as I have been throughout my time here, I’ll be an independent voice fighting for our district,” he said.\n\nHe said he spoke with Johnson over the weekend about his intentions to continue to caucus with the House GOP, but that he had made his decision without input from either party’s leadership.\n\nAsked if he plans to change the party he caucuses with next term if he’s reelected this fall, Kiley responded, “I’m going to do whatever is serves my constituents and so you know that’s a decision that I’ll make at the time.”\n\nKiley has introduced legislation to prohibit mid-decade redistricting nationwide.\n\n“I have been very strongly opposed to this redistricting war – this epidemic of gerrymandering – across the country, ” he said. “I think it’s a terrible thing for democracy.”\n\nSee Full Web Article",
  "links": [
    {
      "url": "https://www.cnn.com/2026/03/09/politics/narrow-house-gop-majority-johnson",
      "text": "already razor-thin GOP majority"
    },
    {
      "url": "https://www.cnn.com/politics/narrow-house-majority-congress-dg",
      "text": "only afford a single defection"
    }
  ],
  "hash": "502f887a7bc9c53b5f3243fcfc4c2e714fc33d01f0a0787b77172e1cfbe93345",
  "scraped_at": "2026-03-10T07:12:00.396092+00:00"
}
