{
  "url": "https://lite.cnn.com/2026/05/01/politics/iran-war-60-day-deadline-congress",
  "title": "War Powers Act: Lawmakers can’t agree when Trump is supposed to get Congress’ approval on Iran war | CNN Politics",
  "date": "2026-05-03T08:19:41.076225+00:00",
  "authors": [
    "Morgan Rimmer"
  ],
  "text": "Source: CNN\n\nA Vietnam-era law says Congress must sign off on the Iran war afterthe conflict hits the 60-day mark.The only problem: Lawmakers can’t agree when that deadline actually hits. And now they’ve left town.\n\nUnder the War Powers Act of 1973, the president has 60 days to conduct military action in response to an imminent threat or an attack on the United States if Congress has not voted to authorize a war. Without explicit congressional authorization, the law says that once that deadline is reached, the president “shall terminate any use of the United States Armed Forces.”\n\nMany lawmakers see Friday, May 1, as the 60-day mark based on President Donald Trump notifying Congress of the beginning of hostilities on March 2. Some Senate Republicans argue that should mark an inflection point where Congress must step in andauthorize the conflict or at least conduct further oversight. But others insist the president can unilaterally extend US military involvement for another 30 days. And some Republicans argue that ceasefire days do not count toward the total.\n\nThe disagreement injects just the latest element of uncertainty into a conflict that has raised questions about Congress’ role in checking the president’s war powers abroad. The extent of that power has been the subject of fierce debate among lawmakers since the war began earlier this year.\n\nThe White House claimed in a statement to CNN on Friday that the war in Iran is over because of the ceasefire between the countries, an argument that sets the administration up to bypass seeking congressional approval.\n\nIn a statement, a senior administration official said that for the purposes of the law, “the hostilities that began on Saturday, February 28 have terminated.”\n\nThe official noted that both the US and Iran had agreed to a two-week ceasefire on April 7 that has since been extended. “There has been no exchange of fire between US Armed Forces and Iran since Tuesday, April 7,” the official said.\n\nThe statement underlines an argument Defense Secretary Pete Hegseth made Thursday in testimony on Capitol Hill, when he said the administration’s understanding of the law is that “the 60-day clock pauses or stops in a ceasefire.”\n\nNorth Carolina Republican Sen. Thom Tillis later questioned Hegseth’s argument. “I felt like the War Powers resolution says in 60 days you have to take some action,” he said, adding that by the time lawmakers return from a week-long recess, “we need to start talking with the administration and in cooperation with them, to get an authorization for the use of military force so the American people understand the Congress is behind what the president is trying to do.”\n\nMeanwhile, some Democrats in Congress argue that the 60-day timeline cannot even be applied to this conflict, saying there was a lack of an imminent threat from Iran at the beginning of the war.\n\n“In my view, this war was illegal from the start, because there was no attack on the United States, there was no imminent threat of attack. Even under the War Powers Act, the president doesn’t get 60 days to make war without congressional approval in the absence of any kind of imminent threat,” said Sen. Adam Schiff.\n\nThe California Democrat has been part of a group of Democratic senators forcing weekly votes on a measure that would require congressional approval for future military action against Iran. Their sixth attempt failed on the Senate floor Thursday afternoon, but, for the first time, Maine Republican Sen. Susan Collins voted with Democrats and Kentucky GOP Sen. Rand Paul.\n\nIn a statement, Collins said, “The Constitution gives Congress an essential role in decisions of war and peace, and the War Powers Act establishes a clear 60-day deadline for Congress to either authorize or end U.S. involvement in foreign hostilities.”\n\n“Further military action against Iran must have a clear mission, achievable goals, and a defined strategy for bringing the conflict to a close. I voted to end the continuation of these military hostilities at this time until such a case is made,” she continued.\n\nOther lawmakers point to a 30-day extension provision in the 1973 law as they insist that the president can continue to conduct the war without congressional approval. Under the law, Trump can extend the 60-day clock for another 30 days if he argues that continued military action is needed to keep service members safe while withdrawing from the war.\n\n“I think the expectation is that he has the ability to extend it for 30 days,” said Sen. Mike Rounds of South Dakota, a member of the Senate Armed Services Committee. “I’d be surprised if he didn’t ask for a 30-day extension. During that time period, we’ll be asking questions.”\n\nSenate Majority Leader John Thune, who controls what measures can receive a vote, signaled on Thursday that his chamber won’t vote on authorizing the war any time soon. “We’re listening carefully to what our members of our conference are saying, and at this point I don’t see that,” he said. “As of right now, I’m not hearing that, no.”\n\nSen. Lisa Murkowski announced Thursday that she plans to introduce a measure on whether to formally authorize the war if she does not see a “credible plan” from the White House in the next week.\n\n“I do not accept that we should engage in open-ended military action without clear direction or accountability. Congress has a role, Congress has to step up and fulfill that role, that obligation that the Constitution assigns to us,” the Alaska Republican said in remarks from the floor.\n\nShe said she will introduce her measure — what’s known as an authorization for use of military force, or AUMF — when the Senate returns from recess the week of May 11 if the administration does not present that plan.\n\nMurkowski added that she stands “firmly behind our troops.” But she stressed that Congress needs to fulfill its constitutional role of declaring war and providing oversight under the Constitution.\n\nFor Missouri Republican Sen. Josh Hawley, “we’re at an inflection point” in the war.\n\n“You know, under the statute, the administration has the ability to request an additional 30 days, and they can certify that statutory framework, if they are ready to draw down militarily. So, they’ve got some options there. Let’s see what happens. But I do think that framework needs to be followed,” he said. “So, you know, we’re at a point — we’re at an inflection point, I think the ball is in the administration’s court, but let’s see what we get.”\n\nMeanwhile, Sen. Tim Kaine scoffed at the idea that some of his GOP colleagues are pointing toward the 90-day mark as a turning point. “And then it’ll be 120 days, and then it’ll be forever. Why don’t we just let Donald Trump wage war against anyone in the world for as long as he wants? That’s what many of them would do,” the Virginia Democrat said.\n\n“I’m just hoping that there are a few who will stand up for their constitutional responsibility. And I don’t think the extension of 60 to 90 is automatic. First, the White House hasn’t asked for it. Second, I think there is a criteria that has to be met to allow the extension,” he added.\n\nSchiff agreed, saying, “I have no expectation that he will do so, because it would require him to say he’s withdrawing forces over the 30-day period. And it’s hard for me to imagine that he is going to commit to that.” And he dismissed the argument that the ceasefire stops the clock from ticking down on the 60-day timeline. “It doesn’t,” he told CNN.\n\nAsked about his GOP colleagues looking for flexibility within the War Powers Act, Schiff replied, “I think they’re torn between the recognition that the Constitution and the law require them to bring this war to an end and a concern with directly confronting the president.”\n\nThis story has been updated with additional details.\n\nCNN’s Sarah Ferris, Zachary Wolf and Dugald McConnell contributed to this report.\n\nCNN’s Sarah Ferris, Zachary Wolf and Dugald McConnell contributed to this report.\n\nSee Full Web Article",
  "links": [
    {
      "url": "https://www.cnn.com/2026/04/25/politics/war-powers-act-trump-iran-war-congress-analysis",
      "text": "the conflict hits the 60-day mark."
    }
  ],
  "hash": "ae288134669424c5fe671dad4f129ce9ec9cde5b05197927ecd411298d6e05f0",
  "scraped_at": "2026-05-03T08:19:41.076237+00:00"
}